pysoniq/__init__.py
pysoniq/fourier.py
pysoniq/gain.py
pysoniq/io.py
pysoniq/loop.py
pysoniq/pause.py
pysoniq/play.py
pysoniq/stop.py
pysoniq/utils.py
pysoniq/visualize.py
pysoniq-0.1.4.dist-info/licenses/LICENSE
pysoniq-0.1.4.dist-info/METADATA
pysoniq-0.1.4.dist-info/WHEEL
pysoniq-0.1.4.dist-info/top_level.txt
pysoniq-0.1.4.dist-info/RECORD
