Metadata-Version: 2.4
Name: pysoniq
Version: 0.1.4
Summary: Lightweight, pure-Python cross-platform audio playback library
Author: laelume
License-Expression: MIT
Project-URL: Homepage, https://github.com/laelume/pysoniq
Project-URL: Repository, https://github.com/laelume/pysoniq
Project-URL: Issues, https://github.com/laelume/pysoniq/issues
Keywords: audio,sound,playback,music,cross-platform,pure-python,audio-playback,audio-player,sound-playback,wav
Classifier: Development Status :: 4 - Beta
Classifier: Intended Audience :: Developers
Classifier: Intended Audience :: Science/Research
Classifier: Operating System :: OS Independent
Classifier: Operating System :: Microsoft :: Windows
Classifier: Operating System :: MacOS
Classifier: Operating System :: POSIX :: Linux
Classifier: Programming Language :: Python :: 3
Classifier: Programming Language :: Python :: 3.8
Classifier: Programming Language :: Python :: 3.9
Classifier: Programming Language :: Python :: 3.10
Classifier: Programming Language :: Python :: 3.11
Classifier: Programming Language :: Python :: 3.12
Classifier: Topic :: Multimedia :: Sound/Audio
Classifier: Topic :: Multimedia :: Sound/Audio :: Players
Classifier: Topic :: Software Development :: Libraries :: Python Modules
Requires-Python: >=3.8
License-File: LICENSE
Requires-Dist: numpy>=1.19.0
Dynamic: license-file
